README.md
setup.py
src/oidcservice/__init__.py
src/oidcservice/client_auth.py
src/oidcservice/exception.py
src/oidcservice/service.py
src/oidcservice/service_context.py
src/oidcservice/service_factory.py
src/oidcservice/state_interface.py
src/oidcservice/util.py
src/oidcservice.egg-info/PKG-INFO
src/oidcservice.egg-info/SOURCES.txt
src/oidcservice.egg-info/dependency_links.txt
src/oidcservice.egg-info/not-zip-safe
src/oidcservice.egg-info/requires.txt
src/oidcservice.egg-info/top_level.txt
src/oidcservice/oauth2/__init__.py
src/oidcservice/oauth2/access_token.py
src/oidcservice/oauth2/authorization.py
src/oidcservice/oauth2/provider_info_discovery.py
src/oidcservice/oauth2/refresh_access_token.py
src/oidcservice/oauth2/utils.py
src/oidcservice/oauth2/client_credentials/__init__.py
src/oidcservice/oauth2/client_credentials/cc_access_token.py
src/oidcservice/oauth2/client_credentials/cc_refresh_access_token.py
src/oidcservice/oidc/__init__.py
src/oidcservice/oidc/access_token.py
src/oidcservice/oidc/authorization.py
src/oidcservice/oidc/check_id.py
src/oidcservice/oidc/check_session.py
src/oidcservice/oidc/end_session.py
src/oidcservice/oidc/provider_info_discovery.py
src/oidcservice/oidc/read_registration.py
src/oidcservice/oidc/refresh_access_token.py
src/oidcservice/oidc/registration.py
src/oidcservice/oidc/userinfo.py
src/oidcservice/oidc/utils.py
src/oidcservice/oidc/webfinger.py
src/oidcservice/oidc/add_on/__init__.py
src/oidcservice/oidc/add_on/pkce.py
src/oidcservice/oidc/add_on/pushed_authorization.py
src/oidcservice/oidc/add_on/status_check.py